structured_output_cookbook/__init__.py
structured_output_cookbook/cli.py
structured_output_cookbook/config.py
structured_output_cookbook/extractor.py
structured_output_cookbook/schemas/__init__.py
structured_output_cookbook/schemas/base.py
structured_output_cookbook/templates/__init__.py
structured_output_cookbook/templates/email.py
structured_output_cookbook/templates/event.py
structured_output_cookbook/templates/job_description.py
structured_output_cookbook/templates/product_review.py
structured_output_cookbook/templates/recipe.py
structured_output_cookbook/utils/__init__.py
structured_output_cookbook/utils/cost_tracker.py
structured_output_cookbook/utils/logger.py
structured_output_cookbook/utils/rate_limiter.py
structured_output_cookbook/utils/schema_loader.py
structured_output_cookbook-0.1.2.dist-info/METADATA
structured_output_cookbook-0.1.2.dist-info/WHEEL
structured_output_cookbook-0.1.2.dist-info/entry_points.txt
structured_output_cookbook-0.1.2.dist-info/licenses/LICENSE
structured_output_cookbook-0.1.2.dist-info/RECORD
