Metadata-Version: 2.4
Name: structured-output-cookbook
Version: 0.1.2
Summary: Extract structured data from text using LLMs with ready-to-use templates
Project-URL: Homepage, https://github.com/mazzasaverio/structured-output-cookbook
Project-URL: Repository, https://github.com/mazzasaverio/structured-output-cookbook
Project-URL: Documentation, https://github.com/mazzasaverio/structured-output-cookbook#readme
Project-URL: Bug Tracker, https://github.com/mazzasaverio/structured-output-cookbook/issues
Project-URL: Changelog, https://github.com/mazzasaverio/structured-output-cookbook/blob/main/CHANGELOG.md
Project-URL: Source Code, https://github.com/mazzasaverio/structured-output-cookbook
Author-email: Saverio Mazza <saverio3107@gmail.com>
Maintainer-email: Saverio Mazza <saverio3107@gmail.com>
License: MIT
License-File: LICENSE
Keywords: api-wrapper,automation,data-extraction,json-extraction,llm,nlp,openai,pydantic,structured-data,templates,text-processing
Classifier: Development Status :: 4 - Beta
Classifier: Intended Audience :: Developers
Classifier: Intended Audience :: Science/Research
Classifier: License :: OSI Approved :: MIT License
Classifier: Operating System :: OS Independent
Classifier: Programming Language :: Python :: 3
Classifier: Programming Language :: Python :: 3.10
Classifier: Programming Language :: Python :: 3.11
Classifier: Programming Language :: Python :: 3.12
Classifier: Programming Language :: Python :: 3.13
Classifier: Topic :: Office/Business
Classifier: Topic :: Scientific/Engineering :: Artificial Intelligence
Classifier: Topic :: Software Development :: Libraries :: Python Modules
Classifier: Topic :: Text Processing :: Linguistic
Classifier: Topic :: Utilities
Requires-Python: >=3.10
Requires-Dist: click>=8.1.7
Requires-Dist: loguru>=0.7.2
Requires-Dist: openai>=1.54.0
Requires-Dist: pydantic>=2.9.0
Requires-Dist: python-dotenv>=1.0.0
Requires-Dist: pyyaml>=6.0.0
Provides-Extra: dev
Requires-Dist: black>=24.0.0; extra == 'dev'
Requires-Dist: ipykernel>=6.25.0; extra == 'dev'
Requires-Dist: jupyter>=1.0.0; extra == 'dev'
Requires-Dist: matplotlib>=3.7.0; extra == 'dev'
Requires-Dist: mypy>=1.13.0; extra == 'dev'
Requires-Dist: pandas>=2.0.0; extra == 'dev'
Requires-Dist: plotly>=5.15.0; extra == 'dev'
Requires-Dist: pre-commit>=4.0.0; extra == 'dev'
Requires-Dist: pytest-cov>=4.0.0; extra == 'dev'
Requires-Dist: pytest-mock>=3.12.0; extra == 'dev'
Requires-Dist: pytest>=8.0.0; extra == 'dev'
Requires-Dist: ruff>=0.8.0; extra == 'dev'
Requires-Dist: seaborn>=0.12.0; extra == 'dev'
